README.md
setup.py
kaggle_tools/__init__.py
kaggle_tools.egg-info/PKG-INFO
kaggle_tools.egg-info/SOURCES.txt
kaggle_tools.egg-info/dependency_links.txt
kaggle_tools.egg-info/top_level.txt
kaggle_tools/classification/__init__.py
kaggle_tools/classification/build_tree.py
kaggle_tools/classification/visualize_tree.py
kaggle_tools/deep-learning/__init__.py
kaggle_tools/deep-learning/model_management.py
kaggle_tools/diagnostic/__init__.py
kaggle_tools/diagnostic/perfromance.py
kaggle_tools/diagnostic/statistical_diagnostic.py
kaggle_tools/features_engineering/__init__.py
kaggle_tools/features_engineering/timestamps.py
kaggle_tools/image_processing/__init__.py
kaggle_tools/image_processing/image_augmentation.py
kaggle_tools/image_processing/image_processing.py
kaggle_tools/metrics/__init__.py
kaggle_tools/metrics/keras.py
kaggle_tools/scale/__init__.py
kaggle_tools/scale/dask.py
kaggle_tools/submission/__init__.py
kaggle_tools/submission/submission.py
kaggle_tools/tests/__init__.py
kaggle_tools/tests/test_keras_metrics.py