Metadata-Version: 1.0
Name: kaggle-tools
Version: 0.0.3
Summary: This is a suite of tools to help you participate in various Kaggle competitions
Home-page: UNKNOWN
Author: Yassine Alouini
Author-email: yassinealouini@outlook.com
License: MIT
Keywords: kaggle machine-learning
Platform: UNKNOWN
